pyspimdbg.py
pyspimdbg-0.2.dist-info/COPYING
pyspimdbg-0.2.dist-info/METADATA
pyspimdbg-0.2.dist-info/WHEEL
pyspimdbg-0.2.dist-info/entry_points.txt
pyspimdbg-0.2.dist-info/top_level.txt
pyspimdbg-0.2.dist-info/RECORD
