Metadata-Version: 2.1
Name: pyspimdbg
Version: 0.2
Home-page: https://github.com/Gabrain24/pyspimdbg
Author: Gabrain24
License-File: COPYING
Requires-Dist: pexpect
